{
    "patienten": [
        {
            "geb": "1934.12.19",
            "geschlecht": "männlich",
            "hnr": 45,
            "id": 4,
            "nachname": "Steiger",
            "ort": "Trier",
            "plz": 36624,
            "strasse": "Hauptstraße",
            "tel": "035324556",
            "titel": "",
            "vorname": "Walter"
        },
        {
            "geb": "2006.01.24",
            "geschlecht": "divers",
            "hnr": 78,
            "id": 11,
            "nachname": "Smith",
            "ort": "Montabauer",
            "plz": 24275,
            "strasse": "Am Markt",
            "tel": "0345878763",
            "titel": "",
            "vorname": "John"
        },
        {
            "geb": "1978.06.29",
            "geschlecht": "männlich",
            "hnr": 98,
            "id": 10,
            "nachname": "Bermel",
            "ort": "Polch",
            "plz": 35487,
            "strasse": "Nachtigallenweg",
            "tel": "01356347561",
            "titel": "Professor",
            "vorname": "Julian"
        },
        {
            "geb": "1995.08.07",
            "geschlecht": "männlich",
            "hnr": 34,
            "id": 9,
            "nachname": "Keil",
            "ort": "Kehrig",
            "plz": 56729,
            "strasse": "Bausbergerstraße",
            "tel": "02345464573",
            "titel": "Doktor",
            "vorname": "Darius"
        },
        {
            "geb": "1991.08.22",
            "geschlecht": "männlich",
            "hnr": 13,
            "id": 8,
            "nachname": "Seuser",
            "ort": "Braunsbedra",
            "plz": 6259,
            "strasse": "An der Kapelle",
            "tel": "09887868763",
            "titel": "Professor",
            "vorname": "Timo"
        },
        {
            "geb": "1988.05.18",
            "geschlecht": "weiblich",
            "hnr": 34,
            "id": 7,
            "nachname": "Sölling",
            "ort": "Koblenz",
            "plz": 87463,
            "strasse": "Kirchstraße",
            "tel": "0997476587439",
            "titel": "Professor",
            "vorname": "Jasmin"
        },
        {
            "geb": "1934.02.03",
            "geschlecht": "weiblich",
            "hnr": 98,
            "id": 6,
            "nachname": "Heck",
            "ort": "Saarbrücken",
            "plz": 56934,
            "strasse": "Am Berg",
            "tel": "046938693486",
            "titel": "",
            "vorname": "Christine"
        },
        {
            "geb": "1934.02.01",
            "geschlecht": "männlich",
            "hnr": 945,
            "id": 5,
            "nachname": "Ried",
            "ort": "Saarbrücken",
            "plz": 45366,
            "strasse": "Bahnhofsstraße",
            "tel": "02194568746",
            "titel": "",
            "vorname": "Hartmut"
        },
        {
            "geb": "1998.10.29",
            "geschlecht": "divers",
            "hnr": 67,
            "id": 2,
            "nachname": "Mustermann",
            "ort": "Mayen",
            "plz": 87546,
            "strasse": "Hauptstraße",
            "tel": "056741366874",
            "titel": "Professor ",
            "vorname": "Maximilian"
        },
        {
            "geb": "1989.07.19",
            "geschlecht": "weiblich",
            "hnr": 15,
            "id": 1,
            "nachname": "Ried",
            "ort": "Binningen",
            "plz": 56784,
            "strasse": "Bahnhofsstraße",
            "tel": "01575239445",
            "titel": "Doktor",
            "vorname": "Jennifer"
        }
    ]
}
